CHANGES.txt
COPYRIGHT.txt
LICENSE.txt
README.txt
bootstrap.py
buildout.cfg
setup.py
src/zamplugin/__init__.py
src/zamplugin.sampledata.egg-info/PKG-INFO
src/zamplugin.sampledata.egg-info/SOURCES.txt
src/zamplugin.sampledata.egg-info/dependency_links.txt
src/zamplugin.sampledata.egg-info/namespace_packages.txt
src/zamplugin.sampledata.egg-info/not-zip-safe
src/zamplugin.sampledata.egg-info/requires.txt
src/zamplugin.sampledata.egg-info/top_level.txt
src/zamplugin/sampledata/README.txt
src/zamplugin/sampledata/__init__.py
src/zamplugin/sampledata/app.zcml
src/zamplugin/sampledata/browser.py
src/zamplugin/sampledata/browser.zcml
src/zamplugin/sampledata/configure.zcml
src/zamplugin/sampledata/ftesting.zcml
src/zamplugin/sampledata/generatesample.pt
src/zamplugin/sampledata/generator.pt
src/zamplugin/sampledata/interfaces.py
src/zamplugin/sampledata/menu.py
src/zamplugin/sampledata/menu.zcml
src/zamplugin/sampledata/plugin.py
src/zamplugin/sampledata/plugin.zcml
src/zamplugin/sampledata/sampledata.pt
src/zamplugin/sampledata/tests.py