Metadata-Version: 1.0
Name: zamplugin.sampledata
Version: 0.6.0
Summary: Sampledata management views for ZAM (Zope Application Management)
Home-page: http://pypi.python.org/pypi/zamplugin.sampledata
Author: Roger Ineichen and the Zope Community
Author-email: zope-dev@zope.org
License: ZPL 2.1
Keywords: zope3 sampledata manager views
Platform: UNKNOWN
Classifier: Development Status :: 4 - Beta
Classifier: Environment :: Web Environment
Classifier: Intended Audience :: Developers
Classifier: License :: OSI Approved :: Zope Public License
Classifier: Programming Language :: Python
Classifier: Natural Language :: English
Classifier: Operating System :: OS Independent
Classifier: Topic :: Internet :: WWW/HTTP
Classifier: Framework :: Zope3
